{
  "main": {
    "id": "7fa10cf795134693",
    "type": "split",
    "children": [
      {
        "id": "87d45fe9b04cedb1",
        "type": "tabs",
        "children": [
          {
            "id": "c3d27a7ebb35013a",
            "type": "leaf",
            "state": {
              "type": "markdown",
              "state": {
                "file": "Toward a Comprehensive Theory of Anti-Intellectualism.md",
                "mode": "source",
                "source": false
              },
              "icon": "lucide-file",
              "title": "Toward a Comprehensive Theory of Anti-Intellectualism"
            }
          },
          {
            "id": "683c7cbc6c858190",
            "type": "leaf",
            "state": {
              "type": "graph",
              "state": {},
              "icon": "lucide-git-fork",
              "title": "Graph view"
            }
          },
          {
            "id": "8029631f8e17dfb7",
            "type": "leaf",
            "state": {
              "type": "markdown",
              "state": {
                "file": "Roman Numerals.md",
                "mode": "source",
                "source": false
              },
              "icon": "lucide-file",
              "title": "Roman Numerals"
            }
          }
        ]
      }
    ],
    "direction": "vertical"
  },
  "left": {
    "id": "e0f234cbbdc51f84",
    "type": "split",
    "children": [
      {
        "id": "401a3c77c4d3d184",
        "type": "tabs",
        "children": [
          {
            "id": "564824a3b39accd3",
            "type": "leaf",
            "state": {
              "type": "file-explorer",
              "state": {
                "sortOrder": "alphabetical",
                "autoReveal": false
              },
              "icon": "lucide-folder-closed",
              "title": "Files"
            }
          },
          {
            "id": "363948121f4ffc78",
            "type": "leaf",
            "state": {
              "type": "search",
              "state": {
                "query": "",
                "matchingCase": false,
                "explainSearch": false,
                "collapseAll": false,
                "extraContext": false,
                "sortOrder": "alphabetical"
              },
              "icon": "lucide-search",
              "title": "Search"
            }
          },
          {
            "id": "a7dc36117cd07e35",
            "type": "leaf",
            "state": {
              "type": "bookmarks",
              "state": {},
              "icon": "lucide-bookmark",
              "title": "Bookmarks"
            }
          }
        ]
      }
    ],
    "direction": "horizontal",
    "width": 300
  },
  "right": {
    "id": "0e903120d1c38318",
    "type": "split",
    "children": [
      {
        "id": "f263687fe77c8212",
        "type": "tabs",
        "children": [
          {
            "id": "763e0692cc10a365",
            "type": "leaf",
            "state": {
              "type": "backlink",
              "state": {
                "collapseAll": false,
                "extraContext": false,
                "sortOrder": "alphabetical",
                "showSearch": false,
                "searchQuery": "",
                "backlinkCollapsed": false,
                "unlinkedCollapsed": true
              },
              "icon": "links-coming-in",
              "title": "Backlinks"
            }
          },
          {
            "id": "7277bb10d231566b",
            "type": "leaf",
            "state": {
              "type": "outgoing-link",
              "state": {
                "linksCollapsed": false,
                "unlinkedCollapsed": true
              },
              "icon": "links-going-out",
              "title": "Outgoing links"
            }
          },
          {
            "id": "9e06399d053d1c65",
            "type": "leaf",
            "state": {
              "type": "tag",
              "state": {
                "sortOrder": "frequency",
                "useHierarchy": true
              },
              "icon": "lucide-tags",
              "title": "Tags"
            }
          },
          {
            "id": "20c1099bda67bb64",
            "type": "leaf",
            "state": {
              "type": "outline",
              "state": {},
              "icon": "lucide-list",
              "title": "Outline"
            }
          }
        ]
      }
    ],
    "direction": "horizontal",
    "width": 300,
    "collapsed": true
  },
  "left-ribbon": {
    "hiddenItems": {
      "switcher:Open quick switcher": false,
      "graph:Open graph view": false,
      "canvas:Create new canvas": false,
      "daily-notes:Open today's daily note": false,
      "templates:Insert template": false,
      "command-palette:Open command palette": false
    }
  },
  "active": "c3d27a7ebb35013a",
  "lastOpenFiles": [
    "config.tsx",
    "Johnson.mdx",
    "Toward a Comprehensive Theory of Anti-Intellectualism.md",
    "i wonder what happesn",
    "Roman Numerals.md",
    "post1.mdx",
    "Untitled.canvas",
    "2024-11-06.md",
    "Johnson.md"
  ]
}